bmi_processor/__init__.py
bmi_processor/bmi_processor.py
bmi_processor_beta-1.0.2.dist-info/LICENSE
bmi_processor_beta-1.0.2.dist-info/METADATA
bmi_processor_beta-1.0.2.dist-info/WHEEL
bmi_processor_beta-1.0.2.dist-info/top_level.txt
bmi_processor_beta-1.0.2.dist-info/RECORD
